pywhichlang=pywhichlang.cp310-win_amd64.pyd
pywhichlang/__init__.py
pywhichlang-0.2.2.dist-info/METADATA
pywhichlang-0.2.2.dist-info/WHEEL
pywhichlang-0.2.2.dist-info/top_level.txt
pywhichlang-0.2.2.dist-info/RECORD
